Workbook

Sheet DRE
A1: DRE
D3: 45292 | E3: =EDATE(D3, 1) | F3: =EDATE(E3, 1) | G3: =EDATE(F3, 1) | H3: =EDATE(G3, 1) | I3: =EDATE(H3, 1) | J3: =EDATE(I3, 1) | K3: =EDATE(J3, 1) | L3: =EDATE(K3, 1) | ... P3: =EDATE(O3, 1)
B4: Receita | D4: =SUMIFS(Vendas!$E:$E,Vendas!$F:$F,">="&EOMONTH(DRE!D$3,-1)+1,Vendas!$F:$F,"<="&EOMONTH(DRE!D$3,0)) | E4: =SUMIFS(Vendas!$E:$E,Vendas!$F:$F,">="&EOMONTH(DRE!E$3,-1)+1,Vendas!$F:$F,"<="&EOMONTH(DRE!E$3,0)) | F4: =SUMIFS(Vendas!$E:$E,Vendas!$F:$F,">="&EOMONTH(DRE!F$3,-1)+1,Vendas!$F:$F,"<="&EOMONTH(DRE!F$3,0)) | G4: =SUMIFS(Vendas!$E:$E,Vendas!$F:$F,">="&EOMONTH(DRE!G$3,-1)+1,Vendas!$F:$F,"<="&EOMONTH(DRE!G$3,0)) | H4: =SUMIFS(Vendas!$E:$E,Vendas!$F:$F,">="&EOMONTH(DRE!H$3,-1)+1,Vendas!$F:$F,"<="&EOMONTH(DRE!H$3,0)) | I4: =SUMIFS(Vendas!$E:$E,Vendas!$F:$F,">="&EOMONTH(DRE!I$3,-1)+1,Vendas!$F:$F,"<="&EOMONTH(DRE!I$3,0)) | J4: =SUMIFS(Vendas!$E:$E,Vendas!$F:$F,">="&EOMONTH(DRE!J$3,-1)+1,Vendas!$F:$F,"<="&EOMONTH(DRE!J$3,0)) | K4: =SUMIFS(Vendas!$E:$E,Vendas!$F:$F,">="&EOMONTH(DRE!K$3,-1)+1,Vendas!$F:$F,"<="&EOMONTH(DRE!K$3,0)) | ... P4: =SUMIFS(Vendas!$E:$E,Vendas!$F:$F,">="&EOMONTH(DRE!P$3,-1)+1,Vendas!$F:$F,"<="&EOMONTH(DRE!P$3,0))
B5: Growth % | E5: =(E4/D4)-1 | F5: =(F4/E4)-1 | G5: =(G4/F4)-1 | H5: =(H4/G4)-1 | I5: =(I4/H4)-1 | J5: =(J4/I4)-1 | K5: =(K4/J4)-1 | L5: =(L4/K4)-1 | ... P5: =(P4/O4)-1
B7: CMV (-) | D7: =-SUM(D9, D11, D13) | E7: =-SUM(E9, E11, E13) | F7: =-SUM(F9, F11, F13) | G7: =-SUM(G9, G11, G13) | H7: =-SUM(H9, H11, H13) | I7: =-SUM(I9, I11, I13) | J7: =-SUM(J9, J11, J13) | K7: =-SUM(K9, K11, K13) | ... P7: =-SUM(P9, P11, P13)
B8: % da Receita | D8: =D7/D4 | E8: =E7/E4 | F8: =F7/F4 | G8: =G7/G4 | H8: =H7/H4 | I8: =I7/I4 | J8: =J7/J4 | K8: =K7/K4 | ... P8: =P7/P4
C9: Armazenagem | D9: =SUMIFS(Custo_Despesas!$B:$B,Custo_Despesas!$C:$C,">="&EOMONTH(DRE!D$3,-1)+1,Custo_Despesas!$C:$C,"<="&EOMONTH(DRE!D$3,0),Custo_Despesas!$A:$A,$C9) | E9: =SUMIFS(Custo_Despesas!$B:$B,Custo_Despesas!$C:$C,">="&EOMONTH(DRE!E$3,-1)+1,Custo_Despesas!$C:$C,"<="&EOMONTH(DRE!E$3,0),Custo_Despesas!$A:$A,$C9) | F9: =SUMIFS(Custo_Despesas!$B:$B,Custo_Despesas!$C:$C,">="&EOMONTH(DRE!F$3,-1)+1,Custo_Despesas!$C:$C,"<="&EOMONTH(DRE!F$3,0),Custo_Despesas!$A:$A,$C9) | G9: =SUMIFS(Custo_Despesas!$B:$B,Custo_Despesas!$C:$C,">="&EOMONTH(DRE!G$3,-1)+1,Custo_Despesas!$C:$C,"<="&EOMONTH(DRE!G$3,0),Custo_Despesas!$A:$A,$C9) | H9: =SUMIFS(Custo_Despesas!$B:$B,Custo_Despesas!$C:$C,">="&EOMONTH(DRE!H$3,-1)+1,Custo_Despesas!$C:$C,"<="&EOMONTH(DRE!H$3,0),Custo_Despesas!$A:$A,$C9) | I9: =SUMIFS(Custo_Despesas!$B:$B,Custo_Despesas!$C:$C,">="&EOMONTH(DRE!I$3,-1)+1,Custo_Despesas!$C:$C,"<="&EOMONTH(DRE!I$3,0),Custo_Despesas!$A:$A,$C9) | J9: =SUMIFS(Custo_Despesas!$B:$B,Custo_Despesas!$C:$C,">="&EOMONTH(DRE!J$3,-1)+1,Custo_Despesas!$C:$C,"<="&EOMONTH(DRE!J$3,0),Custo_Despesas!$A:$A,$C9) | K9: =SUMIFS(Custo_Despesas!$B:$B,Custo_Despesas!$C:$C,">="&EOMONTH(DRE!K$3,-1)+1,Custo_Despesas!$C:$C,"<="&EOMONTH(DRE!K$3,0),Custo_Despesas!$A:$A,$C9) | ... P9: =SUMIFS(Custo_Despesas!$B:$B,Custo_Despesas!$C:$C,">="&EOMONTH(DRE!P$3,-1)+1,Custo_Despesas!$C:$C,"<="&EOMONTH(DRE!P$3,0),Custo_Despesas!$A:$A,$C9)
C10: % da Receita | D10: =D9/D4 | E10: =E9/E4 | F10: =F9/F4 | G10: =G9/G4 | H10: =H9/H4 | I10: =I9/I4 | J10: =J9/J4 | K10: =K9/K4 | ... P10: =P9/P4
C11: Frete | D11: =SUMIFS(Custo_Despesas!$B:$B,Custo_Despesas!$C:$C,">="&EOMONTH(DRE!D$3,-1)+1,Custo_Despesas!$C:$C,"<="&EOMONTH(DRE!D$3,0),Custo_Despesas!$A:$A,$C11) | E11: =SUMIFS(Custo_Despesas!$B:$B,Custo_Despesas!$C:$C,">="&EOMONTH(DRE!E$3,-1)+1,Custo_Despesas!$C:$C,"<="&EOMONTH(DRE!E$3,0),Custo_Despesas!$A:$A,$C11) | F11: =SUMIFS(Custo_Despesas!$B:$B,Custo_Despesas!$C:$C,">="&EOMONTH(DRE!F$3,-1)+1,Custo_Despesas!$C:$C,"<="&EOMONTH(DRE!F$3,0),Custo_Despesas!$A:$A,$C11) | G11: =SUMIFS(Custo_Despesas!$B:$B,Custo_Despesas!$C:$C,">="&EOMONTH(DRE!G$3,-1)+1,Custo_Despesas!$C:$C,"<="&EOMONTH(DRE!G$3,0),Custo_Despesas!$A:$A,$C11) | H11: =SUMIFS(Custo_Despesas!$B:$B,Custo_Despesas!$C:$C,">="&EOMONTH(DRE!H$3,-1)+1,Custo_Despesas!$C:$C,"<="&EOMONTH(DRE!H$3,0),Custo_Despesas!$A:$A,$C11) | I11: =SUMIFS(Custo_Despesas!$B:$B,Custo_Despesas!$C:$C,">="&EOMONTH(DRE!I$3,-1)+1,Custo_Despesas!$C:$C,"<="&EOMONTH(DRE!I$3,0),Custo_Despesas!$A:$A,$C11) | J11: =SUMIFS(Custo_Despesas!$B:$B,Custo_Despesas!$C:$C,">="&EOMONTH(DRE!J$3,-1)+1,Custo_Despesas!$C:$C,"<="&EOMONTH(DRE!J$3,0),Custo_Despesas!$A:$A,$C11) | K11: =SUMIFS(Custo_Despesas!$B:$B,Custo_Despesas!$C:$C,">="&EOMONTH(DRE!K$3,-1)+1,Custo_Despesas!$C:$C,"<="&EOMONTH(DRE!K$3,0),Custo_Despesas!$A:$A,$C11) | ... P11: =SUMIFS(Custo_Despesas!$B:$B,Custo_Despesas!$C:$C,">="&EOMONTH(DRE!P$3,-1)+1,Custo_Despesas!$C:$C,"<="&EOMONTH(DRE!P$3,0),Custo_Despesas!$A:$A,$C11)
C12: % da Receita | D12: =D11/D4 | E12: =E11/E4 | F12: =F11/F4 | G12: =G11/G4 | H12: =H11/H4 | I12: =I11/I4 | J12: =J11/J4 | K12: =K11/K4 | ... P12: =P11/P4
C13: Matéria-prima | D13: =SUMIFS(Custo_Despesas!$B:$B,Custo_Despesas!$C:$C,">="&EOMONTH(DRE!D$3,-1)+1,Custo_Despesas!$C:$C,"<="&EOMONTH(DRE!D$3,0),Custo_Despesas!$A:$A,$C13) | E13: =SUMIFS(Custo_Despesas!$B:$B,Custo_Despesas!$C:$C,">="&EOMONTH(DRE!E$3,-1)+1,Custo_Despesas!$C:$C,"<="&EOMONTH(DRE!E$3,0),Custo_Despesas!$A:$A,$C13) | F13: =SUMIFS(Custo_Despesas!$B:$B,Custo_Despesas!$C:$C,">="&EOMONTH(DRE!F$3,-1)+1,Custo_Despesas!$C:$C,"<="&EOMONTH(DRE!F$3,0),Custo_Despesas!$A:$A,$C13) | G13: =SUMIFS(Custo_Despesas!$B:$B,Custo_Despesas!$C:$C,">="&EOMONTH(DRE!G$3,-1)+1,Custo_Despesas!$C:$C,"<="&EOMONTH(DRE!G$3,0),Custo_Despesas!$A:$A,$C13) | H13: =SUMIFS(Custo_Despesas!$B:$B,Custo_Despesas!$C:$C,">="&EOMONTH(DRE!H$3,-1)+1,Custo_Despesas!$C:$C,"<="&EOMONTH(DRE!H$3,0),Custo_Despesas!$A:$A,$C13) | I13: =SUMIFS(Custo_Despesas!$B:$B,Custo_Despesas!$C:$C,">="&EOMONTH(DRE!I$3,-1)+1,Custo_Despesas!$C:$C,"<="&EOMONTH(DRE!I$3,0),Custo_Despesas!$A:$A,$C13) | J13: =SUMIFS(Custo_Despesas!$B:$B,Custo_Despesas!$C:$C,">="&EOMONTH(DRE!J$3,-1)+1,Custo_Despesas!$C:$C,"<="&EOMONTH(DRE!J$3,0),Custo_Despesas!$A:$A,$C13) | K13: =SUMIFS(Custo_Despesas!$B:$B,Custo_Despesas!$C:$C,">="&EOMONTH(DRE!K$3,-1)+1,Custo_Despesas!$C:$C,"<="&EOMONTH(DRE!K$3,0),Custo_Despesas!$A:$A,$C13) | ... P13: =SUMIFS(Custo_Despesas!$B:$B,Custo_Despesas!$C:$C,">="&EOMONTH(DRE!P$3,-1)+1,Custo_Despesas!$C:$C,"<="&EOMONTH(DRE!P$3,0),Custo_Despesas!$A:$A,$C13)
C14: % da Receita | D14: =D13/D4 | E14: =E13/E4 | F14: =F13/F4 | G14: =G13/G4 | H14: =H13/H4 | I14: =I13/I4 | J14: =J13/J4 | K14: =K13/K4 | ... P14: =P13/P4
B16: Lucro bruto | D16: =D4+D7 | E16: =E4+E7 | F16: =F4+F7 | G16: =G4+G7 | H16: =H4+H7 | I16: =I4+I7 | J16: =J4+J7 | K16: =K4+K7 | ... P16: =P4+P7
B17: Margem Bruta % | D17: =D16/D4 | E17: =E16/E4 | F17: =F16/F4 | G17: =G16/G4 | H17: =H16/H4 | I17: =I16/I4 | J17: =J16/J4 | K17: =K16/K4 | ... P17: =P16/P4
B19: SG&A (-) | D19: =-SUM(D21, D23, D25, D27) | E19: =-SUM(E21, E23, E25, E27) | F19: =-SUM(F21, F23, F25, F27) | G19: =-SUM(G21, G23, G25, G27) | H19: =-SUM(H21, H23, H25, H27) | I19: =-SUM(I21, I23, I25, I27) | J19: =-SUM(J21, J23, J25, J27) | K19: =-SUM(K21, K23, K25, K27) | ... P19: =-SUM(P21, P23, P25, P27)
C21: Marketing | D21: =SUMIFS(Custo_Despesas!$B:$B,Custo_Despesas!$C:$C,">="&EOMONTH(DRE!D$3,-1)+1,Custo_Despesas!$C:$C,"<="&EOMONTH(DRE!D$3,0),Custo_Despesas!$A:$A,$C21) | E21: =SUMIFS(Custo_Despesas!$B:$B,Custo_Despesas!$C:$C,">="&EOMONTH(DRE!E$3,-1)+1,Custo_Despesas!$C:$C,"<="&EOMONTH(DRE!E$3,0),Custo_Despesas!$A:$A,$C21) | F21: =SUMIFS(Custo_Despesas!$B:$B,Custo_Despesas!$C:$C,">="&EOMONTH(DRE!F$3,-1)+1,Custo_Despesas!$C:$C,"<="&EOMONTH(DRE!F$3,0),Custo_Despesas!$A:$A,$C21) | G21: =SUMIFS(Custo_Despesas!$B:$B,Custo_Despesas!$C:$C,">="&EOMONTH(DRE!G$3,-1)+1,Custo_Despesas!$C:$C,"<="&EOMONTH(DRE!G$3,0),Custo_Despesas!$A:$A,$C21) | H21: =SUMIFS(Custo_Despesas!$B:$B,Custo_Despesas!$C:$C,">="&EOMONTH(DRE!H$3,-1)+1,Custo_Despesas!$C:$C,"<="&EOMONTH(DRE!H$3,0),Custo_Despesas!$A:$A,$C21) | I21: =SUMIFS(Custo_Despesas!$B:$B,Custo_Despesas!$C:$C,">="&EOMONTH(DRE!I$3,-1)+1,Custo_Despesas!$C:$C,"<="&EOMONTH(DRE!I$3,0),Custo_Despesas!$A:$A,$C21) | J21: =SUMIFS(Custo_Despesas!$B:$B,Custo_Despesas!$C:$C,">="&EOMONTH(DRE!J$3,-1)+1,Custo_Despesas!$C:$C,"<="&EOMONTH(DRE!J$3,0),Custo_Despesas!$A:$A,$C21) | K21: =SUMIFS(Custo_Despesas!$B:$B,Custo_Despesas!$C:$C,">="&EOMONTH(DRE!K$3,-1)+1,Custo_Despesas!$C:$C,"<="&EOMONTH(DRE!K$3,0),Custo_Despesas!$A:$A,$C21) | ... P21: =SUMIFS(Custo_Despesas!$B:$B,Custo_Despesas!$C:$C,">="&EOMONTH(DRE!P$3,-1)+1,Custo_Despesas!$C:$C,"<="&EOMONTH(DRE!P$3,0),Custo_Despesas!$A:$A,$C21)
C22: % da Receita | D22: =D21/D4 | E22: =E21/E4 | F22: =F21/F4 | G22: =G21/G4 | H22: =H21/H4 | I22: =I21/I4 | J22: =J21/J4 | K22: =K21/K4 | ... P22: =P21/P4
C23: Comercial | D23: =SUMIFS(Custo_Despesas!$B:$B,Custo_Despesas!$C:$C,">="&EOMONTH(DRE!D$3,-1)+1,Custo_Despesas!$C:$C,"<="&EOMONTH(DRE!D$3,0),Custo_Despesas!$A:$A,$C23) | E23: =SUMIFS(Custo_Despesas!$B:$B,Custo_Despesas!$C:$C,">="&EOMONTH(DRE!E$3,-1)+1,Custo_Despesas!$C:$C,"<="&EOMONTH(DRE!E$3,0),Custo_Despesas!$A:$A,$C23) | F23: =SUMIFS(Custo_Despesas!$B:$B,Custo_Despesas!$C:$C,">="&EOMONTH(DRE!F$3,-1)+1,Custo_Despesas!$C:$C,"<="&EOMONTH(DRE!F$3,0),Custo_Despesas!$A:$A,$C23) | G23: =SUMIFS(Custo_Despesas!$B:$B,Custo_Despesas!$C:$C,">="&EOMONTH(DRE!G$3,-1)+1,Custo_Despesas!$C:$C,"<="&EOMONTH(DRE!G$3,0),Custo_Despesas!$A:$A,$C23) | H23: =SUMIFS(Custo_Despesas!$B:$B,Custo_Despesas!$C:$C,">="&EOMONTH(DRE!H$3,-1)+1,Custo_Despesas!$C:$C,"<="&EOMONTH(DRE!H$3,0),Custo_Despesas!$A:$A,$C23) | I23: =SUMIFS(Custo_Despesas!$B:$B,Custo_Despesas!$C:$C,">="&EOMONTH(DRE!I$3,-1)+1,Custo_Despesas!$C:$C,"<="&EOMONTH(DRE!I$3,0),Custo_Despesas!$A:$A,$C23) | J23: =SUMIFS(Custo_Despesas!$B:$B,Custo_Despesas!$C:$C,">="&EOMONTH(DRE!J$3,-1)+1,Custo_Despesas!$C:$C,"<="&EOMONTH(DRE!J$3,0),Custo_Despesas!$A:$A,$C23) | K23: =SUMIFS(Custo_Despesas!$B:$B,Custo_Despesas!$C:$C,">="&EOMONTH(DRE!K$3,-1)+1,Custo_Despesas!$C:$C,"<="&EOMONTH(DRE!K$3,0),Custo_Despesas!$A:$A,$C23) | ... P23: =SUMIFS(Custo_Despesas!$B:$B,Custo_Despesas!$C:$C,">="&EOMONTH(DRE!P$3,-1)+1,Custo_Despesas!$C:$C,"<="&EOMONTH(DRE!P$3,0),Custo_Despesas!$A:$A,$C23)
C24: % da Receita | D24: =D23/D4 | E24: =E23/E4 | F24: =F23/F4 | G24: =G23/G4 | H24: =H23/H4 | I24: =I23/I4 | J24: =J23/J4 | K24: =K23/K4 | ... P24: =P23/P4
C25: Administrativo | D25: =SUMIFS(Custo_Despesas!$B:$B,Custo_Despesas!$C:$C,">="&EOMONTH(DRE!D$3,-1)+1,Custo_Despesas!$C:$C,"<="&EOMONTH(DRE!D$3,0),Custo_Despesas!$A:$A,$C25) | E25: =SUMIFS(Custo_Despesas!$B:$B,Custo_Despesas!$C:$C,">="&EOMONTH(DRE!E$3,-1)+1,Custo_Despesas!$C:$C,"<="&EOMONTH(DRE!E$3,0),Custo_Despesas!$A:$A,$C25) | F25: =SUMIFS(Custo_Despesas!$B:$B,Custo_Despesas!$C:$C,">="&EOMONTH(DRE!F$3,-1)+1,Custo_Despesas!$C:$C,"<="&EOMONTH(DRE!F$3,0),Custo_Despesas!$A:$A,$C25) | G25: =SUMIFS(Custo_Despesas!$B:$B,Custo_Despesas!$C:$C,">="&EOMONTH(DRE!G$3,-1)+1,Custo_Despesas!$C:$C,"<="&EOMONTH(DRE!G$3,0),Custo_Despesas!$A:$A,$C25) | H25: =SUMIFS(Custo_Despesas!$B:$B,Custo_Despesas!$C:$C,">="&EOMONTH(DRE!H$3,-1)+1,Custo_Despesas!$C:$C,"<="&EOMONTH(DRE!H$3,0),Custo_Despesas!$A:$A,$C25) | I25: =SUMIFS(Custo_Despesas!$B:$B,Custo_Despesas!$C:$C,">="&EOMONTH(DRE!I$3,-1)+1,Custo_Despesas!$C:$C,"<="&EOMONTH(DRE!I$3,0),Custo_Despesas!$A:$A,$C25) | J25: =SUMIFS(Custo_Despesas!$B:$B,Custo_Despesas!$C:$C,">="&EOMONTH(DRE!J$3,-1)+1,Custo_Despesas!$C:$C,"<="&EOMONTH(DRE!J$3,0),Custo_Despesas!$A:$A,$C25) | K25: =SUMIFS(Custo_Despesas!$B:$B,Custo_Despesas!$C:$C,">="&EOMONTH(DRE!K$3,-1)+1,Custo_Despesas!$C:$C,"<="&EOMONTH(DRE!K$3,0),Custo_Despesas!$A:$A,$C25) | ... P25: =SUMIFS(Custo_Despesas!$B:$B,Custo_Despesas!$C:$C,">="&EOMONTH(DRE!P$3,-1)+1,Custo_Despesas!$C:$C,"<="&EOMONTH(DRE!P$3,0),Custo_Despesas!$A:$A,$C25)
C26: % da Receita | D26: =D25/D4 | E26: =E25/E4 | F26: =F25/F4 | G26: =G25/G4 | H26: =H25/H4 | I26: =I25/I4 | J26: =J25/J4 | K26: =K25/K4 | ... P26: =P25/P4
C27: Folha | D27: =SUMIFS(Folha!$C:$C, Folha!$A:$A, ">= " & EOMONTH(DRE!D$3, -1) + 1, Folha!$A:$A, "<= " & EOMONTH(DRE!D$3, 0))+SUMIFS(Folha!$D:$D, Folha!$A:$A, ">= " & EOMONTH(DRE!D$3, -1) + 1, Folha!$A:$A, "<= " & EOMONTH(DRE!D$3, 0))+SUMIFS(Folha!$E:$E, Folha!$A:$A, ">= " & EOMONTH(DRE!D$3, -1) + 1, Folha!$A:$A, "<= " & EOMONTH(DRE!D$3, 0)) | E27: =SUMIFS(Folha!$C:$C, Folha!$A:$A, ">= " & EOMONTH(DRE!E$3, -1) + 1, Folha!$A:$A, "<= " & EOMONTH(DRE!E$3, 0))+SUMIFS(Folha!$D:$D, Folha!$A:$A, ">= " & EOMONTH(DRE!E$3, -1) + 1, Folha!$A:$A, "<= " & EOMONTH(DRE!E$3, 0))+SUMIFS(Folha!$E:$E, Folha!$A:$A, ">= " & EOMONTH(DRE!E$3, -1) + 1, Folha!$A:$A, "<= " & EOMONTH(DRE!E$3, 0)) | F27: =SUMIFS(Folha!$C:$C, Folha!$A:$A, ">= " & EOMONTH(DRE!F$3, -1) + 1, Folha!$A:$A, "<= " & EOMONTH(DRE!F$3, 0))+SUMIFS(Folha!$D:$D, Folha!$A:$A, ">= " & EOMONTH(DRE!F$3, -1) + 1, Folha!$A:$A, "<= " & EOMONTH(DRE!F$3, 0))+SUMIFS(Folha!$E:$E, Folha!$A:$A, ">= " & EOMONTH(DRE!F$3, -1) + 1, Folha!$A:$A, "<= " & EOMONTH(DRE!F$3, 0)) | G27: =SUMIFS(Folha!$C:$C, Folha!$A:$A, ">= " & EOMONTH(DRE!G$3, -1) + 1, Folha!$A:$A, "<= " & EOMONTH(DRE!G$3, 0))+SUMIFS(Folha!$D:$D, Folha!$A:$A, ">= " & EOMONTH(DRE!G$3, -1) + 1, Folha!$A:$A, "<= " & EOMONTH(DRE!G$3, 0))+SUMIFS(Folha!$E:$E, Folha!$A:$A, ">= " & EOMONTH(DRE!G$3, -1) + 1, Folha!$A:$A, "<= " & EOMONTH(DRE!G$3, 0)) | H27: =SUMIFS(Folha!$C:$C, Folha!$A:$A, ">= " & EOMONTH(DRE!H$3, -1) + 1, Folha!$A:$A, "<= " & EOMONTH(DRE!H$3, 0))+SUMIFS(Folha!$D:$D, Folha!$A:$A, ">= " & EOMONTH(DRE!H$3, -1) + 1, Folha!$A:$A, "<= " & EOMONTH(DRE!H$3, 0))+SUMIFS(Folha!$E:$E, Folha!$A:$A, ">= " & EOMONTH(DRE!H$3, -1) + 1, Folha!$A:$A, "<= " & EOMONTH(DRE!H$3, 0)) | I27: =SUMIFS(Folha!$C:$C, Folha!$A:$A, ">= " & EOMONTH(DRE!I$3, -1) + 1, Folha!$A:$A, "<= " & EOMONTH(DRE!I$3, 0))+SUMIFS(Folha!$D:$D, Folha!$A:$A, ">= " & EOMONTH(DRE!I$3, -1) + 1, Folha!$A:$A, "<= " & EOMONTH(DRE!I$3, 0))+SUMIFS(Folha!$E:$E, Folha!$A:$A, ">= " & EOMONTH(DRE!I$3, -1) + 1, Folha!$A:$A, "<= " & EOMONTH(DRE!I$3, 0)) | J27: =SUMIFS(Folha!$C:$C, Folha!$A:$A, ">= " & EOMONTH(DRE!J$3, -1) + 1, Folha!$A:$A, "<= " & EOMONTH(DRE!J$3, 0))+SUMIFS(Folha!$D:$D, Folha!$A:$A, ">= " & EOMONTH(DRE!J$3, -1) + 1, Folha!$A:$A, "<= " & EOMONTH(DRE!J$3, 0))+SUMIFS(Folha!$E:$E, Folha!$A:$A, ">= " & EOMONTH(DRE!J$3, -1) + 1, Folha!$A:$A, "<= " & EOMONTH(DRE!J$3, 0)) | K27: =SUMIFS(Folha!$C:$C, Folha!$A:$A, ">= " & EOMONTH(DRE!K$3, -1) + 1, Folha!$A:$A, "<= " & EOMONTH(DRE!K$3, 0))+SUMIFS(Folha!$D:$D, Folha!$A:$A, ">= " & EOMONTH(DRE!K$3, -1) + 1, Folha!$A:$A, "<= " & EOMONTH(DRE!K$3, 0))+SUMIFS(Folha!$E:$E, Folha!$A:$A, ">= " & EOMONTH(DRE!K$3, -1) + 1, Folha!$A:$A, "<= " & EOMONTH(DRE!K$3, 0)) | ... P27: =SUMIFS(Folha!$C:$C, Folha!$A:$A, ">= " & EOMONTH(DRE!P$3, -1) + 1, Folha!$A:$A, "<= " & EOMONTH(DRE!P$3, 0))+SUMIFS(Folha!$D:$D, Folha!$A:$A, ">= " & EOMONTH(DRE!P$3, -1) + 1, Folha!$A:$A, "<= " & EOMONTH(DRE!P$3, 0))+SUMIFS(Folha!$E:$E, Folha!$A:$A, ">= " & EOMONTH(DRE!P$3, -1) + 1, Folha!$A:$A, "<= " & EOMONTH(DRE!P$3, 0))
C28: % da Receita | D28: =D27/D4 | E28: =E27/E4 | F28: =F27/F4 | G28: =G27/G4 | H28: =H27/H4 | I28: =I27/I4 | J28: =J27/J4 | K28: =K27/K4 | ... P28: =P27/P4
B30: EBITDA | D30: =D4+D7+D19 | E30: =E4+E7+E19 | F30: =F4+F7+F19 | G30: =G4+G7+G19 | H30: =H4+H7+H19 | I30: =I4+I7+I19 | J30: =J4+J7+J19 | K30: =K4+K7+K19 | ... P30: =P4+P7+P19
B31: Margem EBITDA % | D31: =D30/D4 | E31: =E30/E4 | F31: =F30/F4 | G31: =G30/G4 | H31: =H30/H4 | I31: =I30/I4 | J31: =J30/J4 | K31: =K30/K4 | ... P31: =P30/P4
B33: D&A (-) | D33: =-Investimentos!J1 | E33: =-Investimentos!K1 | F33: =-Investimentos!L1 | G33: =-Investimentos!M1 | H33: =-Investimentos!N1 | I33: =-Investimentos!O1 | J33: =-Investimentos!P1 | K33: =-Investimentos!Q1 | ... P33: =-Investimentos!V1
B35: EBIT | D35: =D30+D33 | E35: =E30+E33 | F35: =F30+F33 | G35: =G30+G33 | H35: =H30+H33 | I35: =I30+I33 | J35: =J30+J33 | K35: =K30+K33 | ... P35: =P30+P33
B36: Margem Operacional % | D36: =D35/D4 | E36: =E35/E4 | F36: =F35/F4 | G36: =G35/G4 | H36: =H35/H4 | I36: =I35/I4 | J36: =J35/J4 | K36: =K35/K4 | ... P36: =P35/P4
B38: Juros (-) | D38: =IFERROR(-Financiamento!J$5, 0) | E38: =IFERROR(-Financiamento!K$5, 0) | F38: =IFERROR(-Financiamento!L$5, 0) | G38: =IFERROR(-Financiamento!M$5, 0) | H38: =IFERROR(-Financiamento!N$5, 0) | I38: =IFERROR(-Financiamento!O$5, 0) | J38: =IFERROR(-Financiamento!P$5, 0) | K38: =IFERROR(-Financiamento!Q$5, 0) | ... P38: =IFERROR(-Financiamento!V$5, 0)
B40: EBT | D40: =D35+D38 | E40: =E35+E38 | F40: =F35+F38 | G40: =G35+G38 | H40: =H35+H38 | I40: =I35+I38 | J40: =J35+J38 | K40: =K35+K38 | ... P40: =P35+P38
B41: % da Receita | D41: =D40/D4 | E41: =E40/E4 | F41: =F40/F4 | G41: =G40/G4 | H41: =H40/H4 | I41: =I40/I4 | J41: =J40/J4 | K41: =K40/K4 | ... P41: =P40/P4
B43: Prejuizo Acumulado *
C44: Inicio | D44: 0 | E44: =D47 | F44: =E47 | G44: =F47 | H44: =G47 | I44: =H47 | J44: =I47 | K44: =J47 | L44: =K47 | ... P44: =O47
C45: Saldo Adquirido | D45: =-IF(D40<0,-D40,0) | E45: =-IF(E40<0,-E40,0) | F45: =-IF(F40<0,-F40,0) | G45: =-IF(G40<0,-G40,0) | H45: =-IF(H40<0,-H40,0) | I45: =-IF(I40<0,-I40,0) | J45: =-IF(J40<0,-J40,0) | K45: =-IF(K40<0,-K40,0) | ... P45: =-IF(P40<0,-P40,0)
C46: Saldo Utilizado | D46: =IF(D$40>0, MIN(D$40*30%, -D$44), 0) | E46: =IF(E$40>0, MIN(E$40*30%, -E$44), 0) | F46: =IF(F$40>0, MIN(F$40*30%, -F$44), 0) | G46: =IF(G$40>0, MIN(G$40*30%, -G$44), 0) | H46: =IF(H$40>0, MIN(H$40*30%, -H$44), 0) | I46: =IF(I$40>0, MIN(I$40*30%, -I$44), 0) | J46: =IF(J$40>0, MIN(J$40*30%, -J$44), 0) | K46: =IF(K$40>0, MIN(K$40*30%, -K$44), 0) | ... P46: =IF(P$40>0, MIN(P$40*30%, -P$44), 0)
C47: Final | D47: =SUM(D44:D46) | E47: =SUM(E44:E46) | F47: =SUM(F44:F46) | G47: =SUM(G44:G46) | H47: =SUM(H44:H46) | I47: =SUM(I44:I46) | J47: =SUM(J44:J46) | K47: =SUM(K44:K46) | ... P47: =SUM(P44:P46)
B49: Base de calculo | D49: =IF(D40<0,0,D40-D46) | E49: =IF(E40<0,0,E40-E46) | F49: =IF(F40<0,0,F40-F46) | G49: =IF(G40<0,0,G40-G46) | H49: =IF(H40<0,0,H40-H46) | I49: =IF(I40<0,0,I40-I46) | J49: =IF(J40<0,0,J40-J46) | K49: =IF(K40<0,0,K40-K46) | ... P49: =IF(P40<0,0,P40-P46)
B51: Impostos (-) | D51: =-D49*0.3 | E51: =-E49*0.3 | F51: =-F49*0.3 | G51: =-G49*0.3 | H51: =-H49*0.3 | I51: =-I49*0.3 | J51: =-J49*0.3 | K51: =-K49*0.3 | ... P51: =-P49*0.3
B52: Taxa Efetiva de Imposto % | D52: =ABS(D51)/D35 | E52: =ABS(E51)/E35 | F52: =ABS(F51)/F35 | G52: =ABS(G51)/G35 | H52: =ABS(H51)/H35 | I52: =ABS(I51)/I35 | J52: =ABS(J51)/J35 | K52: =ABS(K51)/K35 | ... P52: =ABS(P51)/P35
B54: Lucro (prejuízo) líquido | D54: =SUM(D51,D40) | E54: =SUM(E51,E40) | F54: =SUM(F51,F40) | G54: =SUM(G51,G40) | H54: =SUM(H51,H40) | I54: =SUM(I51,I40) | J54: =SUM(J51,J40) | K54: =SUM(K51,K40) | ... P54: =SUM(P51,P40)

Sheet DFC

Sheet BP

Sheet Vendas
A1: Cliente | B1: Produto | C1: Quantidade | D1: Valor_Unitário | E1: Valor_Líquido | F1: Mês
A2: Laboratório C | B2: Produto A | C2: 22 | D2: 2125.7529 | E2: 46766.564 | F2: 45292
A3: Hospital D | B3: Produto B | C3: 15 | D3: 2199.3057 | E3: 32989.585 | F3: 45292
A4: Clínica B | B4: Produto A | C4: 33 | D4: 2237.699 | E4: 73844.067 | F4: 45292
A5: Clínica B | B5: Produto B | C5: 20 | D5: 1279.6075 | E5: 25592.15 | F5: 45292
A6: Hospital D | B6: Produto A | C6: 14 | D6: 1353.5376 | E6: 18949.527 | F6: 45292
A7: Laboratório C | B7: Produto C | C7: 5 | D7: 1950.6378 | E7: 9753.1892 | F7: 45292
A8: Laboratório C | B8: Produto C | C8: 12 | D8: 2361.7992 | E8: 28341.59 | F8: 45292
A9: Clínica B | B9: Produto A | C9: 34 | D9: 1474.2949 | E9: 50126.026 | F9: 45292
A10: Laboratório C | B10: Produto A | C10: 34 | D10: 1882.46 | E10: 64003.64 | F10: 45292
A11: Hospital A | B11: Produto A | C11: 30 | D11: 2024.4731 | E11: 60734.193 | F11: 45292
A12: Clínica B | B12: Produto C | C12: 34 | D12: 1677.9229 | E12: 57049.379 | F12: 45292
A13: Laboratório C | B13: Produto A | C13: 30 | D13: 2070.6737 | E13: 62120.21 | F13: 45292
... A261: Hospital A | B261: Produto A | C261: 63 | D261: 2082.2993 | E261: 131184.86 | F261: 45658

Sheet Investimentos
A1: Mês | B1: Descrição | C1: Valor | E1: TOTAL D&A | J1: =SUM(J6:J18) | K1: =SUM(K6:K18) | L1: =SUM(L6:L18) | M1: =SUM(M6:M18) | N1: =SUM(N6:N18) | O1: =SUM(O6:O18) | P1: =SUM(P6:P18) | Q1: =SUM(Q6:Q18) | ... V1: =SUM(V6:V18)
A2: 45292 | B2: Expansão | C2: 75649.452
A3: 45292 | B3: Expansão | C3: 20257.461 | E3: WATERFALL DE DEPRECIAÇÃO
A4: 45292 | B4: Software | C4: 69567.147
A5: 45323 | B5: Equipamento | C5: 48439.441 | E5: Ativo | F5: Descrição | G5: Valor | H5: Vida Útil (anos) | I5: Deprec. Mensal | J5: 45292 | K5: =EDATE(J5,1) | L5: =EDATE(K5,1) | M5: =EDATE(L5,1) | N5: =EDATE(M5,1) | O5: =EDATE(N5,1) | P5: =EDATE(O5,1) | Q5: =EDATE(P5,1) | R5: =EDATE(Q5,1) | ... V5: =EDATE(U5,1)
A6: 45323 | B6: Equipamento | C6: 83535.787 | E6: 1 | F6: Expansão | G6: 75649.452 | H6: 3 | I6: =G6/(H6*12) | J6: =IF(AND(J5>=DATE(2024,2,1),J5<DATE(2027,2,1)),I6,0) | K6: =IF(AND(K5>=DATE(2024,2,1),K5<DATE(2027,2,1)),I6,0) | L6: =IF(AND(L5>=DATE(2024,2,1),L5<DATE(2027,2,1)),I6,0) | M6: =IF(AND(M5>=DATE(2024,2,1),M5<DATE(2027,2,1)),I6,0) | N6: =IF(AND(N5>=DATE(2024,2,1),N5<DATE(2027,2,1)),I6,0) | O6: =IF(AND(O5>=DATE(2024,2,1),O5<DATE(2027,2,1)),I6,0) | P6: =IF(AND(P5>=DATE(2024,2,1),P5<DATE(2027,2,1)),I6,0) | Q6: =IF(AND(Q5>=DATE(2024,2,1),Q5<DATE(2027,2,1)),I6,0) | R6: =IF(AND(R5>=DATE(2024,2,1),R5<DATE(2027,2,1)),I6,0) | S6: =IF(AND(S5>=DATE(2024,2,1),S5<DATE(2027,2,1)),I6,0) | T6: =IF(AND(T5>=DATE(2024,2,1),T5<DATE(2027,2,1)),I6,0) | U6: =IF(AND(U5>=DATE(2024,2,1),U5<DATE(2027,2,1)),I6,0) | V6: =IF(AND(V5>=DATE(2024,2,1),V5<DATE(2027,2,1)),I6,0)
A7: 45323 | B7: Equipamento | C7: 27439.251 | E7: 2 | F7: Expansão | G7: 20257.461 | H7: 3 | I7: =G7/(H7*12) | J7: =IF(AND(J5>=DATE(2024,2,1),J5<DATE(2027,2,1)),I7,0) | K7: =IF(AND(K5>=DATE(2024,2,1),K5<DATE(2027,2,1)),I7,0) | L7: =IF(AND(L5>=DATE(2024,2,1),L5<DATE(2027,2,1)),I7,0) | M7: =IF(AND(M5>=DATE(2024,2,1),M5<DATE(2027,2,1)),I7,0) | N7: =IF(AND(N5>=DATE(2024,2,1),N5<DATE(2027,2,1)),I7,0) | O7: =IF(AND(O5>=DATE(2024,2,1),O5<DATE(2027,2,1)),I7,0) | P7: =IF(AND(P5>=DATE(2024,2,1),P5<DATE(2027,2,1)),I7,0) | Q7: =IF(AND(Q5>=DATE(2024,2,1),Q5<DATE(2027,2,1)),I7,0) | R7: =IF(AND(R5>=DATE(2024,2,1),R5<DATE(2027,2,1)),I7,0) | S7: =IF(AND(S5>=DATE(2024,2,1),S5<DATE(2027,2,1)),I7,0) | T7: =IF(AND(T5>=DATE(2024,2,1),T5<DATE(2027,2,1)),I7,0) | U7: =IF(AND(U5>=DATE(2024,2,1),U5<DATE(2027,2,1)),I7,0) | V7: =IF(AND(V5>=DATE(2024,2,1),V5<DATE(2027,2,1)),I7,0)
A8: 45352 | B8: Equipamento | C8: 67056.181 | E8: 3 | F8: Software | G8: 69567.147 | H8: 5 | I8: =G8/(H8*12) | J8: =IF(AND(J5>=DATE(2024,2,1),J5<DATE(2029,2,1)),I8,0) | K8: =IF(AND(K5>=DATE(2024,2,1),K5<DATE(2029,2,1)),I8,0) | L8: =IF(AND(L5>=DATE(2024,2,1),L5<DATE(2029,2,1)),I8,0) | M8: =IF(AND(M5>=DATE(2024,2,1),M5<DATE(2029,2,1)),I8,0) | N8: =IF(AND(N5>=DATE(2024,2,1),N5<DATE(2029,2,1)),I8,0) | O8: =IF(AND(O5>=DATE(2024,2,1),O5<DATE(2029,2,1)),I8,0) | P8: =IF(AND(P5>=DATE(2024,2,1),P5<DATE(2029,2,1)),I8,0) | Q8: =IF(AND(Q5>=DATE(2024,2,1),Q5<DATE(2029,2,1)),I8,0) | R8: =IF(AND(R5>=DATE(2024,2,1),R5<DATE(2029,2,1)),I8,0) | S8: =IF(AND(S5>=DATE(2024,2,1),S5<DATE(2029,2,1)),I8,0) | T8: =IF(AND(T5>=DATE(2024,2,1),T5<DATE(2029,2,1)),I8,0) | U8: =IF(AND(U5>=DATE(2024,2,1),U5<DATE(2029,2,1)),I8,0) | V8: =IF(AND(V5>=DATE(2024,2,1),V5<DATE(2029,2,1)),I8,0)
A9: 45352 | B9: Equipamento | C9: 58477.831 | E9: 4 | F9: Equipamento | G9: 48439.441 | H9: 3 | I9: =G9/(H9*12) | J9: =IF(AND(J5>=DATE(2024,3,1),J5<DATE(2027,3,1)),I9,0) | K9: =IF(AND(K5>=DATE(2024,3,1),K5<DATE(2027,3,1)),I9,0) | L9: =IF(AND(L5>=DATE(2024,3,1),L5<DATE(2027,3,1)),I9,0) | M9: =IF(AND(M5>=DATE(2024,3,1),M5<DATE(2027,3,1)),I9,0) | N9: =IF(AND(N5>=DATE(2024,3,1),N5<DATE(2027,3,1)),I9,0) | O9: =IF(AND(O5>=DATE(2024,3,1),O5<DATE(2027,3,1)),I9,0) | P9: =IF(AND(P5>=DATE(2024,3,1),P5<DATE(2027,3,1)),I9,0) | Q9: =IF(AND(Q5>=DATE(2024,3,1),Q5<DATE(2027,3,1)),I9,0) | R9: =IF(AND(R5>=DATE(2024,3,1),R5<DATE(2027,3,1)),I9,0) | S9: =IF(AND(S5>=DATE(2024,3,1),S5<DATE(2027,3,1)),I9,0) | T9: =IF(AND(T5>=DATE(2024,3,1),T5<DATE(2027,3,1)),I9,0) | U9: =IF(AND(U5>=DATE(2024,3,1),U5<DATE(2027,3,1)),I9,0) | V9: =IF(AND(V5>=DATE(2024,3,1),V5<DATE(2027,3,1)),I9,0)
A10: 45352 | B10: Equipamento | C10: 71386.042 | E10: 5 | F10: Equipamento | G10: 83535.787 | H10: 3 | I10: =G10/(H10*12) | J10: =IF(AND(J5>=DATE(2024,3,1),J5<DATE(2027,3,1)),I10,0) | K10: =IF(AND(K5>=DATE(2024,3,1),K5<DATE(2027,3,1)),I10,0) | L10: =IF(AND(L5>=DATE(2024,3,1),L5<DATE(2027,3,1)),I10,0) | M10: =IF(AND(M5>=DATE(2024,3,1),M5<DATE(2027,3,1)),I10,0) | N10: =IF(AND(N5>=DATE(2024,3,1),N5<DATE(2027,3,1)),I10,0) | O10: =IF(AND(O5>=DATE(2024,3,1),O5<DATE(2027,3,1)),I10,0) | P10: =IF(AND(P5>=DATE(2024,3,1),P5<DATE(2027,3,1)),I10,0) | Q10: =IF(AND(Q5>=DATE(2024,3,1),Q5<DATE(2027,3,1)),I10,0) | R10: =IF(AND(R5>=DATE(2024,3,1),R5<DATE(2027,3,1)),I10,0) | S10: =IF(AND(S5>=DATE(2024,3,1),S5<DATE(2027,3,1)),I10,0) | T10: =IF(AND(T5>=DATE(2024,3,1),T5<DATE(2027,3,1)),I10,0) | U10: =IF(AND(U5>=DATE(2024,3,1),U5<DATE(2027,3,1)),I10,0) | V10: =IF(AND(V5>=DATE(2024,3,1),V5<DATE(2027,3,1)),I10,0)
A11: 45383 | B11: Equipamento | C11: 25188.288 | E11: 6 | F11: Equipamento | G11: 27439.251 | H11: 3 | I11: =G11/(H11*12) | J11: =IF(AND(J5>=DATE(2024,3,1),J5<DATE(2027,3,1)),I11,0) | K11: =IF(AND(K5>=DATE(2024,3,1),K5<DATE(2027,3,1)),I11,0) | L11: =IF(AND(L5>=DATE(2024,3,1),L5<DATE(2027,3,1)),I11,0) | M11: =IF(AND(M5>=DATE(2024,3,1),M5<DATE(2027,3,1)),I11,0) | N11: =IF(AND(N5>=DATE(2024,3,1),N5<DATE(2027,3,1)),I11,0) | O11: =IF(AND(O5>=DATE(2024,3,1),O5<DATE(2027,3,1)),I11,0) | P11: =IF(AND(P5>=DATE(2024,3,1),P5<DATE(2027,3,1)),I11,0) | Q11: =IF(AND(Q5>=DATE(2024,3,1),Q5<DATE(2027,3,1)),I11,0) | R11: =IF(AND(R5>=DATE(2024,3,1),R5<DATE(2027,3,1)),I11,0) | S11: =IF(AND(S5>=DATE(2024,3,1),S5<DATE(2027,3,1)),I11,0) | T11: =IF(AND(T5>=DATE(2024,3,1),T5<DATE(2027,3,1)),I11,0) | U11: =IF(AND(U5>=DATE(2024,3,1),U5<DATE(2027,3,1)),I11,0) | V11: =IF(AND(V5>=DATE(2024,3,1),V5<DATE(2027,3,1)),I11,0)
A12: 45383 | B12: Equipamento | C12: 66398.703 | E12: 7 | F12: Equipamento | G12: 67056.181 | H12: 3 | I12: =G12/(H12*12) | J12: =IF(AND(J5>=DATE(2024,4,1),J5<DATE(2027,4,1)),I12,0) | K12: =IF(AND(K5>=DATE(2024,4,1),K5<DATE(2027,4,1)),I12,0) | L12: =IF(AND(L5>=DATE(2024,4,1),L5<DATE(2027,4,1)),I12,0) | M12: =IF(AND(M5>=DATE(2024,4,1),M5<DATE(2027,4,1)),I12,0) | N12: =IF(AND(N5>=DATE(2024,4,1),N5<DATE(2027,4,1)),I12,0) | O12: =IF(AND(O5>=DATE(2024,4,1),O5<DATE(2027,4,1)),I12,0) | P12: =IF(AND(P5>=DATE(2024,4,1),P5<DATE(2027,4,1)),I12,0) | Q12: =IF(AND(Q5>=DATE(2024,4,1),Q5<DATE(2027,4,1)),I12,0) | R12: =IF(AND(R5>=DATE(2024,4,1),R5<DATE(2027,4,1)),I12,0) | S12: =IF(AND(S5>=DATE(2024,4,1),S5<DATE(2027,4,1)),I12,0) | T12: =IF(AND(T5>=DATE(2024,4,1),T5<DATE(2027,4,1)),I12,0) | U12: =IF(AND(U5>=DATE(2024,4,1),U5<DATE(2027,4,1)),I12,0) | V12: =IF(AND(V5>=DATE(2024,4,1),V5<DATE(2027,4,1)),I12,0)
A13: 45383 | B13: Equipamento | C13: 64918.767 | E13: 8 | F13: Equipamento | G13: 58477.831 | H13: 3 | I13: =G13/(H13*12) | J13: =IF(AND(J5>=DATE(2024,4,1),J5<DATE(2027,4,1)),I13,0) | K13: =IF(AND(K5>=DATE(2024,4,1),K5<DATE(2027,4,1)),I13,0) | L13: =IF(AND(L5>=DATE(2024,4,1),L5<DATE(2027,4,1)),I13,0) | M13: =IF(AND(M5>=DATE(2024,4,1),M5<DATE(2027,4,1)),I13,0) | N13: =IF(AND(N5>=DATE(2024,4,1),N5<DATE(2027,4,1)),I13,0) | O13: =IF(AND(O5>=DATE(2024,4,1),O5<DATE(2027,4,1)),I13,0) | P13: =IF(AND(P5>=DATE(2024,4,1),P5<DATE(2027,4,1)),I13,0) | Q13: =IF(AND(Q5>=DATE(2024,4,1),Q5<DATE(2027,4,1)),I13,0) | R13: =IF(AND(R5>=DATE(2024,4,1),R5<DATE(2027,4,1)),I13,0) | S13: =IF(AND(S5>=DATE(2024,4,1),S5<DATE(2027,4,1)),I13,0) | T13: =IF(AND(T5>=DATE(2024,4,1),T5<DATE(2027,4,1)),I13,0) | U13: =IF(AND(U5>=DATE(2024,4,1),U5<DATE(2027,4,1)),I13,0) | V13: =IF(AND(V5>=DATE(2024,4,1),V5<DATE(2027,4,1)),I13,0)
E14: 9 | F14: Equipamento | G14: 71386.042 | H14: 3 | I14: =G14/(H14*12) | J14: =IF(AND(J5>=DATE(2024,4,1),J5<DATE(2027,4,1)),I14,0) | K14: =IF(AND(K5>=DATE(2024,4,1),K5<DATE(2027,4,1)),I14,0) | L14: =IF(AND(L5>=DATE(2024,4,1),L5<DATE(2027,4,1)),I14,0) | M14: =IF(AND(M5>=DATE(2024,4,1),M5<DATE(2027,4,1)),I14,0) | N14: =IF(AND(N5>=DATE(2024,4,1),N5<DATE(2027,4,1)),I14,0) | O14: =IF(AND(O5>=DATE(2024,4,1),O5<DATE(2027,4,1)),I14,0) | P14: =IF(AND(P5>=DATE(2024,4,1),P5<DATE(2027,4,1)),I14,0) | Q14: =IF(AND(Q5>=DATE(2024,4,1),Q5<DATE(2027,4,1)),I14,0) | R14: =IF(AND(R5>=DATE(2024,4,1),R5<DATE(2027,4,1)),I14,0) | S14: =IF(AND(S5>=DATE(2024,4,1),S5<DATE(2027,4,1)),I14,0) | T14: =IF(AND(T5>=DATE(2024,4,1),T5<DATE(2027,4,1)),I14,0) | U14: =IF(AND(U5>=DATE(2024,4,1),U5<DATE(2027,4,1)),I14,0) | V14: =IF(AND(V5>=DATE(2024,4,1),V5<DATE(2027,4,1)),I14,0)
E15: 10 | F15: Equipamento | G15: 25188.288 | H15: 3 | I15: =G15/(H15*12) | J15: =IF(AND(J5>=DATE(2024,5,1),J5<DATE(2027,5,1)),I15,0) | K15: =IF(AND(K5>=DATE(2024,5,1),K5<DATE(2027,5,1)),I15,0) | L15: =IF(AND(L5>=DATE(2024,5,1),L5<DATE(2027,5,1)),I15,0) | M15: =IF(AND(M5>=DATE(2024,5,1),M5<DATE(2027,5,1)),I15,0) | N15: =IF(AND(N5>=DATE(2024,5,1),N5<DATE(2027,5,1)),I15,0) | O15: =IF(AND(O5>=DATE(2024,5,1),O5<DATE(2027,5,1)),I15,0) | P15: =IF(AND(P5>=DATE(2024,5,1),P5<DATE(2027,5,1)),I15,0) | Q15: =IF(AND(Q5>=DATE(2024,5,1),Q5<DATE(2027,5,1)),I15,0) | R15: =IF(AND(R5>=DATE(2024,5,1),R5<DATE(2027,5,1)),I15,0) | S15: =IF(AND(S5>=DATE(2024,5,1),S5<DATE(2027,5,1)),I15,0) | T15: =IF(AND(T5>=DATE(2024,5,1),T5<DATE(2027,5,1)),I15,0) | U15: =IF(AND(U5>=DATE(2024,5,1),U5<DATE(2027,5,1)),I15,0) | V15: =IF(AND(V5>=DATE(2024,5,1),V5<DATE(2027,5,1)),I15,0)
E16: 11 | F16: Equipamento | G16: 66398.703 | H16: 3 | I16: =G16/(H16*12) | J16: =IF(AND(J5>=DATE(2024,5,1),J5<DATE(2027,5,1)),I16,0) | K16: =IF(AND(K5>=DATE(2024,5,1),K5<DATE(2027,5,1)),I16,0) | L16: =IF(AND(L5>=DATE(2024,5,1),L5<DATE(2027,5,1)),I16,0) | M16: =IF(AND(M5>=DATE(2024,5,1),M5<DATE(2027,5,1)),I16,0) | N16: =IF(AND(N5>=DATE(2024,5,1),N5<DATE(2027,5,1)),I16,0) | O16: =IF(AND(O5>=DATE(2024,5,1),O5<DATE(2027,5,1)),I16,0) | P16: =IF(AND(P5>=DATE(2024,5,1),P5<DATE(2027,5,1)),I16,0) | Q16: =IF(AND(Q5>=DATE(2024,5,1),Q5<DATE(2027,5,1)),I16,0) | R16: =IF(AND(R5>=DATE(2024,5,1),R5<DATE(2027,5,1)),I16,0) | S16: =IF(AND(S5>=DATE(2024,5,1),S5<DATE(2027,5,1)),I16,0) | T16: =IF(AND(T5>=DATE(2024,5,1),T5<DATE(2027,5,1)),I16,0) | U16: =IF(AND(U5>=DATE(2024,5,1),U5<DATE(2027,5,1)),I16,0) | V16: =IF(AND(V5>=DATE(2024,5,1),V5<DATE(2027,5,1)),I16,0)
E17: 12 | F17: Equipamento | G17: 64918.767 | H17: 3 | I17: =G17/(H17*12) | J17: =IF(AND(J5>=DATE(2024,5,1),J5<DATE(2027,5,1)),I17,0) | K17: =IF(AND(K5>=DATE(2024,5,1),K5<DATE(2027,5,1)),I17,0) | L17: =IF(AND(L5>=DATE(2024,5,1),L5<DATE(2027,5,1)),I17,0) | M17: =IF(AND(M5>=DATE(2024,5,1),M5<DATE(2027,5,1)),I17,0) | N17: =IF(AND(N5>=DATE(2024,5,1),N5<DATE(2027,5,1)),I17,0) | O17: =IF(AND(O5>=DATE(2024,5,1),O5<DATE(2027,5,1)),I17,0) | P17: =IF(AND(P5>=DATE(2024,5,1),P5<DATE(2027,5,1)),I17,0) | Q17: =IF(AND(Q5>=DATE(2024,5,1),Q5<DATE(2027,5,1)),I17,0) | R17: =IF(AND(R5>=DATE(2024,5,1),R5<DATE(2027,5,1)),I17,0) | S17: =IF(AND(S5>=DATE(2024,5,1),S5<DATE(2027,5,1)),I17,0) | T17: =IF(AND(T5>=DATE(2024,5,1),T5<DATE(2027,5,1)),I17,0) | U17: =IF(AND(U5>=DATE(2024,5,1),U5<DATE(2027,5,1)),I17,0) | V17: =IF(AND(V5>=DATE(2024,5,1),V5<DATE(2027,5,1)),I17,0)

Sheet Folha
A1: Mês | B1: Funcionário | C1: Salário_Bruto | D1: Encargos | E1: Benefícios
A2: 45292 | B2: João | C2: 33821.186 | D2: 7853.5348 | E2: 1919.6045
A3: 45292 | B3: Maria | C3: 29343.886 | D3: 7098.5942 | E3: 5587.6033
A4: 45292 | B4: Pedro | C4: 19943.021 | D4: 7562.5489 | E4: 4385.9273
A5: 45292 | B5: Ana | C5: 17011.228 | D5: 10867.512 | E5: 3058.5578
A6: 45323 | B6: João | C6: 16531.109 | D6: 10737.48 | E6: 5163.9819
A7: 45323 | B7: Maria | C7: 23711.563 | D7: 10560.048 | E7: 2839.568
A8: 45323 | B8: Pedro | C8: 21406.189 | D8: 9571.1783 | E8: 3908.7981
A9: 45323 | B9: Ana | C9: 29710.608 | D9: 6894.2101 | E9: 4253.4489
A10: 45352 | B10: João | C10: 26505.451 | D10: 7251.697 | E10: 2699.6613
A11: 45352 | B11: Maria | C11: 21409.861 | D11: 8109.6041 | E11: 5535.1194
A12: 45352 | B12: Pedro | C12: 18859.353 | D12: 9862.535 | E12: 4673.2305
A13: 45352 | B13: Ana | C13: 18378.043 | D13: 5108.7681 | E13: 3960.4527
... A53: 45658 | B53: Ana | C53: 16376.868 | D53: 7775.3385 | E53: 4923.8032

Sheet Financiamento
A1: Parcela | B1: Data_Pagamento | C1: Prestação | D1: Juros | E1: Amortização | F1: Saldo_Devedor_Antes | G1: Saldo_Devedor_Depois
A2: 3 | B2: 45383 | C2: 47073.47 | D2: 9254.82 | E2: 37818.65 | F2: 925482.32 | G2: 887663.67
A3: 4 | B3: 45413 | C3: 47073.47 | D3: 8876.64 | E3: 38196.84 | F3: 887663.67 | G3: 849466.84
A4: 5 | B4: 45444 | C4: 47073.47 | D4: 8494.67 | E4: 38578.8 | F4: 849466.84 | G4: 810888.03
A5: 6 | B5: 45474 | C5: 47073.47 | D5: 8108.88 | E5: 38964.59 | F5: 810888.03 | G5: 771923.44
A6: 7 | B6: 45505 | C6: 47073.47 | D6: 7719.23 | E6: 39354.24 | F6: 771923.44 | G6: 732569.2
A7: 8 | B7: 45536 | C7: 47073.47 | D7: 7325.69 | E7: 39747.78 | F7: 732569.2 | G7: 692821.42
A8: 9 | B8: 45566 | C8: 47073.47 | D8: 6928.21 | E8: 40145.26 | F8: 692821.42 | G8: 652676.16
A9: 10 | B9: 45597 | C9: 47073.47 | D9: 6526.76 | E9: 40546.71 | F9: 652676.16 | G9: 612129.45
A10: 11 | B10: 45627 | C10: 47073.47 | D10: 6121.29 | E10: 40952.18 | F10: 612129.45 | G10: 571177.28
A11: 12 | B11: 45658 | C11: 47073.47 | D11: 5711.77 | E11: 41361.7 | F11: 571177.28 | G11: 529815.58
A12: 13 | B12: 45689 | C12: 47073.47 | D12: 5298.16 | E12: 41775.32 | F12: 529815.58 | G12: 488040.26
A13: 14 | B13: 45717 | C13: 47073.47 | D13: 4880.4 | E13: 42193.07 | F13: 488040.26 | G13: 445847.19
... A23: 24 | B23: 46023 | C23: 47073.47 | D23: 466.07 | E23: 46607.4 | F23: 46607.4 | G23: 0

Sheet Custo_Despesas
A1: Categoria | B1: Valor | C1: Mês
A2: Armazenagem | B2: 4542.2939 | C2: 45292
A3: Frete | B3: 3502.0425 | C3: 45292
A4: Frete | B4: 5294.7561 | C4: 45292
A5: Armazenagem | B5: 1490.5146 | C5: 45292
A6: Armazenagem | B6: 8599.3031 | C6: 45292
A7: Frete | B7: 1411.7168 | C7: 45292
A8: Frete | B8: 3995.652 | C8: 45292
A9: Matéria-prima | B9: 136680.42 | C9: 45292
A10: Matéria-prima | B10: 111277.11 | C10: 45292
A11: Frete | B11: 3576.2405 | C11: 45292
A12: Armazenagem | B12: 3323.312 | C12: 45292
A13: Armazenagem | B13: 1144.7228 | C13: 45292
... A521: Comercial | B521: 6205.5051 | C521: 45658
